{
	"competition": "Junior Mixed Sunday (U12 - U16)",
	"season": 2026,
	"totalFixtures": 123,
	"totalRounds": 18,
	"fixtures": [
		{
			"round": 1,
			"date": "2026-04-26",
			"day": "Sunday",
			"time": "12:45",
			"homeTeamId": "3vmZv3YLmq",
			"awayTeamId": "3vmZv9nLmq",
			"homeTeamName": "Aintree SC U14 Juniors - D Mixed AINTREE BOYS",
			"awayTeamName": "Moonee Valley Knights SC U14 Juniors - D Mixed Moonee Valley Knights U14 (David)",
			"address": "Aintree North Recreation Reserve Field 1",
			"coordinates": "",
			"homeScore": 3,
			"awayScore": 4,
			"status": "complete"
		},
		{
			"round": 1,
			"date": "2026-04-26",
			"day": "Sunday",
			"time": "12:30",
			"homeTeamId": "k2KpRJ56mY",
			"awayTeamId": "bgdMXLL2KE",
			"homeTeamName": "Truganina Lions FC U14 Juniors - D Mixed Boys U14 - D",
			"awayTeamName": "Barnstoneworth United FC U14 Juniors - D Mixed BUFC U14",
			"address": "Alcock Road Reserve Pitch 2",
			"coordinates": "",
			"homeScore": 3,
			"awayScore": 3,
			"status": "complete"
		},
		{
			"round": 1,
			"date": "2026-04-26",
			"day": "Sunday",
			"time": "12:00",
			"homeTeamId": "bam1nkkrNw",
			"awayTeamId": "R1K3BvL3NQ",
			"homeTeamName": "Footscray Rangers FC U14 Juniors - C Mixed Martin",
			"awayTeamName": "Melbourne City FC U14 Juniors - D Mixed",
			"address": "Hansen Reserve Pitch 2 - Junior Pitch",
			"coordinates": "",
			"homeScore": 2,
			"awayScore": 1,
			"status": "complete"
		},
		{
			"round": 1,
			"date": "2026-04-26",
			"day": "Sunday",
			"time": "11:00",
			"homeTeamId": "gld4pGXGdW",
			"awayTeamId": "6lNbpDpwdx",
			"homeTeamName": "Gisborne SC U14 Juniors - D Mixed 14JS",
			"awayTeamName": "Williamstown SC U14 Juniors - D Mixed Under 14D Boys",
			"address": "Dixon Field Reserve Pitch E (Junior)",
			"coordinates": "",
			"homeScore": 3,
			"awayScore": 1,
			"status": "complete"
		},
		{
			"round": 1,
			"date": "2026-04-26",
			"day": "Sunday",
			"time": "10:45",
			"homeTeamId": "nPmrBk05mo",
			"awayTeamId": "Bjma0G03dR",
			"homeTeamName": "Hoppers Crossing SC U14 Juniors - D Mixed u14 Frank",
			"awayTeamName": "Wyndham FC U14 Juniors - D Mixed Under 14 D",
			"address": "Grange Reserve - Hoppers Crossing Pitch 1",
			"coordinates": "",
			"homeScore": 13,
			"awayScore": 2,
			"status": "complete"
		},
		{
			"round": 1,
			"date": "2026-04-26",
			"day": "Sunday",
			"time": "10:00",
			"homeTeamId": "kemAbxpxNB",
			"awayTeamId": "1pN6pqv7d0",
			"homeTeamName": "Macedon Rangers SC U14 Juniors - D Mixed U14 Mixed Juniors MRSC",
			"awayTeamName": "Sunbury United FC U14 Juniors - D Mixed Sunbury United FC U14",
			"address": "Romsey Recreation Reserve Pitch 2",
			"coordinates": "",
			"homeScore": 1,
			"awayScore": 10,
			"status": "complete"
		},
		{
			"round": 2,
			"date": "2026-05-03",
			"day": "Sunday",
			"time": "12:05",
			"homeTeamId": "R1K3BvL3NQ",
			"awayTeamId": "AnmYzg4rNz",
			"homeTeamName": "Melbourne City FC U14 Juniors - D Mixed",
			"awayTeamName": "Maidstone United SC U14 Juniors - D Mixed Mick",
			"address": "Edwards Reserve Main Pitch",
			"coordinates": "",
			"homeScore": 2,
			"awayScore": 1,
			"status": "complete"
		},
		{
			"round": 2,
			"date": "2026-05-03",
			"day": "Sunday",
			"time": "11:30",
			"homeTeamId": "1pN6pqv7d0",
			"awayTeamId": "bam1nkkrNw",
			"homeTeamName": "Sunbury United FC U14 Juniors - D Mixed Sunbury United FC U14",
			"awayTeamName": "Footscray Rangers FC U14 Juniors - C Mixed Martin",
			"address": "Langama Park Pitch 2 - Full Field",
			"coordinates": "",
			"homeScore": 3,
			"awayScore": 12,
			"status": "complete"
		},
		{
			"round": 2,
			"date": "2026-05-03",
			"day": "Sunday",
			"time": "11:00",
			"homeTeamId": "gld4pGXGdW",
			"awayTeamId": "3vmZv3YLmq",
			"homeTeamName": "Gisborne SC U14 Juniors - D Mixed 14JS",
			"awayTeamName": "Aintree SC U14 Juniors - D Mixed AINTREE BOYS",
			"address": "Dixon Field Reserve Pitch E (Junior)",
			"coordinates": "",
			"homeScore": 3,
			"awayScore": 6,
			"status": "complete"
		},
		{
			"round": 2,
			"date": "2026-05-03",
			"day": "Sunday",
			"time": "10:00",
			"homeTeamId": "bgdMXLL2KE",
			"awayTeamId": "nPmrBk05mo",
			"homeTeamName": "Barnstoneworth United FC U14 Juniors - D Mixed BUFC U14",
			"awayTeamName": "Hoppers Crossing SC U14 Juniors - D Mixed u14 Frank",
			"address": "JT Gray Reserve Pitch 6- BUFC",
			"coordinates": "",
			"homeScore": 1,
			"awayScore": 5,
			"status": "complete"
		},
		{
			"round": 2,
			"date": "2026-05-03",
			"day": "Sunday",
			"time": "10:00",
			"homeTeamId": "Bjma0G03dR",
			"awayTeamId": "kemAbxpxNB",
			"homeTeamName": "Wyndham FC U14 Juniors - D Mixed Under 14 D",
			"awayTeamName": "Macedon Rangers SC U14 Juniors - D Mixed U14 Mixed Juniors MRSC",
			"address": "Wyndham Vale North Reserve Main Pitch B",
			"coordinates": "",
			"homeScore": 2,
			"awayScore": 1,
			"status": "complete"
		},
		{
			"round": 3,
			"date": "2026-05-10",
			"day": "Sunday",
			"time": "10:50",
			"homeTeamId": "AnmYzg4rNz",
			"awayTeamId": "1pN6pqv7d0",
			"homeTeamName": "Maidstone United SC U14 Juniors - D Mixed Mick",
			"awayTeamName": "Sunbury United FC U14 Juniors - D Mixed Sunbury United FC U14",
			"address": "Scovell Reserve Main Pitch",
			"coordinates": "-37.784639,144.878892",
			"status": "pending"
		},
		{
			"round": 3,
			"date": "2026-05-10",
			"day": "Sunday",
			"time": "11:00",
			"homeTeamId": "bam1nkkrNw",
			"awayTeamId": "Bjma0G03dR",
			"homeTeamName": "Footscray Rangers FC U14 Juniors - C Mixed Martin",
			"awayTeamName": "Wyndham FC U14 Juniors - D Mixed Under 14 D",
			"address": "Hansen Reserve Pitch 2 - Junior Pitch",
			"coordinates": "-37.8042,144.872777",
			"status": "pending"
		},
		{
			"round": 3,
			"date": "2026-05-10",
			"day": "Sunday",
			"time": "11:15",
			"homeTeamId": "3vmZv3YLmq",
			"awayTeamId": "R1K3BOqGNQ",
			"homeTeamName": "Aintree SC U14 Juniors - D Mixed AINTREE BOYS",
			"awayTeamName": "Satellite City United SC U14 Juniors - D Mixed Costa",
			"address": "Aintree North Recreation Reserve Field 1",
			"coordinates": "-37.714012,144.665373",
			"status": "pending"
		},
		{
			"round": 3,
			"date": "2026-05-10",
			"day": "Sunday",
			"time": "11:15",
			"homeTeamId": "kemAbxpxNB",
			"awayTeamId": "bgdMXLL2KE",
			"homeTeamName": "Macedon Rangers SC U14 Juniors - D Mixed U14 Mixed Juniors MRSC",
			"awayTeamName": "Barnstoneworth United FC U14 Juniors - D Mixed BUFC U14",
			"address": "Romsey Recreation Reserve Pitch 2",
			"coordinates": "-37.353194,144.749117",
			"status": "pending"
		},
		{
			"round": 3,
			"date": "2026-05-10",
			"day": "Sunday",
			"time": "12:15",
			"homeTeamId": "k2KpRJ56mY",
			"awayTeamId": "gld4pGXGdW",
			"homeTeamName": "Truganina Lions FC U14 Juniors - D Mixed Boys U14 - D",
			"awayTeamName": "Gisborne SC U14 Juniors - D Mixed 14JS",
			"address": "Alcock Road Reserve Pitch 2",
			"coordinates": "-37.829359,144.720192",
			"status": "pending"
		},
		{
			"round": 3,
			"date": "2026-05-10",
			"day": "Sunday",
			"time": "12:20",
			"homeTeamId": "nPmrBk05mo",
			"awayTeamId": "6lNbpDpwdx",
			"homeTeamName": "Hoppers Crossing SC U14 Juniors - D Mixed u14 Frank",
			"awayTeamName": "Williamstown SC U14 Juniors - D Mixed Under 14D Boys",
			"address": "Grange Reserve - Hoppers Crossing Pitch 1",
			"coordinates": "-37.861006,144.67653",
			"status": "pending"
		},
		{
			"round": 3,
			"date": "2026-05-10",
			"day": "Sunday",
			"time": "13:30",
			"homeTeamId": "3vmZv9nLmq",
			"awayTeamId": "R1K3BvL3NQ",
			"homeTeamName": "Moonee Valley Knights SC U14 Juniors - D Mixed Moonee Valley Knights U14 (David)",
			"awayTeamName": "Melbourne City FC U14 Juniors - D Mixed",
			"address": "Avondale Heights Reserve Pitch 1",
			"coordinates": "-37.76242,144.858824",
			"status": "pending"
		},
		{
			"round": 4,
			"date": "2026-05-16",
			"day": "Sunday",
			"time": "09:35",
			"homeTeamId": "bgdMXLL2KE",
			"awayTeamId": "bam1nkkrNw",
			"homeTeamName": "Barnstoneworth United FC U14 Juniors - D Mixed BUFC U14",
			"awayTeamName": "Footscray Rangers FC U14 Juniors - C Mixed Martin",
			"address": "JT Gray Reserve Pitch 6- BUFC",
			"coordinates": "-37.857002,144.865559",
			"status": "pending"
		},
		{
			"round": 4,
			"date": "2026-05-17",
			"day": "Sunday",
			"time": "10:00",
			"homeTeamId": "gld4pGXGdW",
			"awayTeamId": "nPmrBk05mo",
			"homeTeamName": "Gisborne SC U14 Juniors - D Mixed 14JS",
			"awayTeamName": "Hoppers Crossing SC U14 Juniors - D Mixed u14 Frank",
			"address": "Dixon Field Reserve Pitch E (Junior)",
			"coordinates": "-37.483554,144.582761",
			"status": "pending"
		},
		{
			"round": 4,
			"date": "2026-05-17",
			"day": "Sunday",
			"time": "10:00",
			"homeTeamId": "1pN6pqv7d0",
			"awayTeamId": "3vmZv9nLmq",
			"homeTeamName": "Sunbury United FC U14 Juniors - D Mixed Sunbury United FC U14",
			"awayTeamName": "Moonee Valley Knights SC U14 Juniors - D Mixed Moonee Valley Knights U14 (David)",
			"address": "Langama Park Pitch 2 - Full Field",
			"coordinates": "-37.586728,144.709286",
			"status": "pending"
		},
		{
			"round": 4,
			"date": "2026-05-17",
			"day": "Sunday",
			"time": "10:15",
			"homeTeamId": "6lNbpDpwdx",
			"awayTeamId": "kemAbxpxNB",
			"homeTeamName": "Williamstown SC U14 Juniors - D Mixed Under 14D Boys",
			"awayTeamName": "Macedon Rangers SC U14 Juniors - D Mixed U14 Mixed Juniors MRSC",
			"address": "JT Gray Reserve Pitch 1 - WSC",
			"coordinates": "-37.857002,144.865559",
			"status": "pending"
		},
		{
			"round": 4,
			"date": "2026-05-17",
			"day": "Sunday",
			"time": "11:00",
			"homeTeamId": "Bjma0G03dR",
			"awayTeamId": "AnmYzg4rNz",
			"homeTeamName": "Wyndham FC U14 Juniors - D Mixed Under 14 D",
			"awayTeamName": "Maidstone United SC U14 Juniors - D Mixed Mick",
			"address": "Wyndham Vale North Reserve Main Pitch B",
			"coordinates": "-37.898902,144.624443",
			"status": "pending"
		},
		{
			"round": 4,
			"date": "2026-05-17",
			"day": "Sunday",
			"time": "12:00",
			"homeTeamId": "R1K3BvL3NQ",
			"awayTeamId": "R1K3BOqGNQ",
			"homeTeamName": "Melbourne City FC U14 Juniors - D Mixed",
			"awayTeamName": "Satellite City United SC U14 Juniors - D Mixed Costa",
			"address": "Edwards Reserve Main Pitch",
			"coordinates": "-37.827616,144.870036",
			"status": "pending"
		},
		{
			"round": 4,
			"date": "2026-05-17",
			"day": "Sunday",
			"time": "13:00",
			"homeTeamId": "k2KpRJ56mY",
			"awayTeamId": "3vmZv3YLmq",
			"homeTeamName": "Truganina Lions FC U14 Juniors - D Mixed Boys U14 - D",
			"awayTeamName": "Aintree SC U14 Juniors - D Mixed AINTREE BOYS",
			"address": "Alcock Road Reserve Pitch 3",
			"coordinates": "-37.829359,144.720192",
			"status": "pending"
		},
		{
			"round": 5,
			"date": "2026-05-24",
			"day": "Sunday",
			"time": "10:15",
			"homeTeamId": "3vmZv3YLmq",
			"awayTeamId": "R1K3BvL3NQ",
			"homeTeamName": "Aintree SC U14 Juniors - D Mixed AINTREE BOYS",
			"awayTeamName": "Melbourne City FC U14 Juniors - D Mixed",
			"address": "Aintree North Recreation Reserve Field 1",
			"coordinates": "-37.714012,144.665373",
			"status": "pending"
		},
		{
			"round": 5,
			"date": "2026-05-24",
			"day": "Sunday",
			"time": "11:15",
			"homeTeamId": "R1K3BOqGNQ",
			"awayTeamId": "1pN6pqv7d0",
			"homeTeamName": "Satellite City United SC U14 Juniors - D Mixed Costa",
			"awayTeamName": "Sunbury United FC U14 Juniors - D Mixed Sunbury United FC U14",
			"address": "Kurunjang Recreation Reserve Pitch 1 (S)",
			"coordinates": "-37.6742,144.584",
			"status": "pending"
		},
		{
			"round": 5,
			"date": "2026-05-24",
			"day": "Sunday",
			"time": "11:15",
			"homeTeamId": "kemAbxpxNB",
			"awayTeamId": "gld4pGXGdW",
			"homeTeamName": "Macedon Rangers SC U14 Juniors - D Mixed U14 Mixed Juniors MRSC",
			"awayTeamName": "Gisborne SC U14 Juniors - D Mixed 14JS",
			"address": "Romsey Recreation Reserve Pitch 2",
			"coordinates": "-37.353194,144.749117",
			"status": "pending"
		},
		{
			"round": 5,
			"date": "2026-05-24",
			"day": "Sunday",
			"time": "11:15",
			"homeTeamId": "AnmYzg4rNz",
			"awayTeamId": "bgdMXLL2KE",
			"homeTeamName": "Maidstone United SC U14 Juniors - D Mixed Mick",
			"awayTeamName": "Barnstoneworth United FC U14 Juniors - D Mixed BUFC U14",
			"address": "Scovell Reserve Main Pitch",
			"coordinates": "-37.784639,144.878892",
			"status": "pending"
		},
		{
			"round": 5,
			"date": "2026-05-24",
			"day": "Sunday",
			"time": "11:45",
			"homeTeamId": "nPmrBk05mo",
			"awayTeamId": "k2KpRJ56mY",
			"homeTeamName": "Hoppers Crossing SC U14 Juniors - D Mixed u14 Frank",
			"awayTeamName": "Truganina Lions FC U14 Juniors - D Mixed Boys U14 - D",
			"address": "Grange Reserve - Hoppers Crossing Pitch 1",
			"coordinates": "-37.861006,144.67653",
			"status": "pending"
		},
		{
			"round": 5,
			"date": "2026-05-24",
			"day": "Sunday",
			"time": "12:15",
			"homeTeamId": "bam1nkkrNw",
			"awayTeamId": "6lNbpDpwdx",
			"homeTeamName": "Footscray Rangers FC U14 Juniors - C Mixed Martin",
			"awayTeamName": "Williamstown SC U14 Juniors - D Mixed Under 14D Boys",
			"address": "Hansen Reserve Pitch 2 - Junior Pitch",
			"coordinates": "-37.8042,144.872777",
			"status": "pending"
		},
		{
			"round": 5,
			"date": "2026-05-24",
			"day": "Sunday",
			"time": "12:40",
			"homeTeamId": "3vmZv9nLmq",
			"awayTeamId": "Bjma0G03dR",
			"homeTeamName": "Moonee Valley Knights SC U14 Juniors - D Mixed Moonee Valley Knights U14 (David)",
			"awayTeamName": "Wyndham FC U14 Juniors - D Mixed Under 14 D",
			"address": "Avondale Heights Reserve Pitch 1",
			"coordinates": "-37.76242,144.858824",
			"status": "pending"
		},
		{
			"round": 6,
			"date": "2026-05-31",
			"day": "Sunday",
			"time": "10:15",
			"homeTeamId": "bgdMXLL2KE",
			"awayTeamId": "3vmZv9nLmq",
			"homeTeamName": "Barnstoneworth United FC U14 Juniors - D Mixed BUFC U14",
			"awayTeamName": "Moonee Valley Knights SC U14 Juniors - D Mixed Moonee Valley Knights U14 (David)",
			"address": "JT Gray Reserve Pitch 6- BUFC",
			"coordinates": "-37.857002,144.865559",
			"status": "pending"
		},
		{
			"round": 6,
			"date": "2026-05-31",
			"day": "Sunday",
			"time": "11:00",
			"homeTeamId": "gld4pGXGdW",
			"awayTeamId": "bam1nkkrNw",
			"homeTeamName": "Gisborne SC U14 Juniors - D Mixed 14JS",
			"awayTeamName": "Footscray Rangers FC U14 Juniors - C Mixed Martin",
			"address": "Dixon Field Reserve Pitch E (Junior)",
			"coordinates": "-37.483554,144.582761",
			"status": "pending"
		},
		{
			"round": 6,
			"date": "2026-05-31",
			"day": "Sunday",
			"time": "11:15",
			"homeTeamId": "k2KpRJ56mY",
			"awayTeamId": "kemAbxpxNB",
			"homeTeamName": "Truganina Lions FC U14 Juniors - D Mixed Boys U14 - D",
			"awayTeamName": "Macedon Rangers SC U14 Juniors - D Mixed U14 Mixed Juniors MRSC",
			"address": "Alcock Road Reserve Pitch 3",
			"coordinates": "-37.829359,144.720192",
			"status": "pending"
		},
		{
			"round": 6,
			"date": "2026-05-31",
			"day": "Sunday",
			"time": "11:30",
			"homeTeamId": "nPmrBk05mo",
			"awayTeamId": "3vmZv3YLmq",
			"homeTeamName": "Hoppers Crossing SC U14 Juniors - D Mixed u14 Frank",
			"awayTeamName": "Aintree SC U14 Juniors - D Mixed AINTREE BOYS",
			"address": "Grange Reserve - Hoppers Crossing Pitch 3 - Synthetic",
			"coordinates": "-37.861006,144.67653",
			"status": "pending"
		},
		{
			"round": 6,
			"date": "2026-05-31",
			"day": "Sunday",
			"time": "11:30",
			"homeTeamId": "1pN6pqv7d0",
			"awayTeamId": "R1K3BvL3NQ",
			"homeTeamName": "Sunbury United FC U14 Juniors - D Mixed Sunbury United FC U14",
			"awayTeamName": "Melbourne City FC U14 Juniors - D Mixed",
			"address": "Langama Park Pitch 2 - Full Field",
			"coordinates": "-37.586728,144.709286",
			"status": "pending"
		},
		{
			"round": 6,
			"date": "2026-05-31",
			"day": "Sunday",
			"time": "13:00",
			"homeTeamId": "Bjma0G03dR",
			"awayTeamId": "R1K3BOqGNQ",
			"homeTeamName": "Wyndham FC U14 Juniors - D Mixed Under 14 D",
			"awayTeamName": "Satellite City United SC U14 Juniors - D Mixed Costa",
			"address": "Wyndham Vale North Reserve Main Pitch A",
			"coordinates": "-37.898902,144.624443",
			"status": "pending"
		},
		{
			"round": 6,
			"date": "2026-05-31",
			"day": "Sunday",
			"time": "13:45",
			"homeTeamId": "6lNbpDpwdx",
			"awayTeamId": "AnmYzg4rNz",
			"homeTeamName": "Williamstown SC U14 Juniors - D Mixed Under 14D Boys",
			"awayTeamName": "Maidstone United SC U14 Juniors - D Mixed Mick",
			"address": "JT Gray Reserve Pitch 1 - WSC",
			"coordinates": "-37.857002,144.865559",
			"status": "pending"
		},
		{
			"round": 7,
			"date": "2026-06-14",
			"day": "Sunday",
			"time": "11:00",
			"homeTeamId": "bam1nkkrNw",
			"awayTeamId": "k2KpRJ56mY",
			"homeTeamName": "Footscray Rangers FC U14 Juniors - C Mixed Martin",
			"awayTeamName": "Truganina Lions FC U14 Juniors - D Mixed Boys U14 - D",
			"address": "Hansen Reserve Pitch 2 - Junior Pitch",
			"coordinates": "-37.8042,144.872777",
			"status": "pending"
		},
		{
			"round": 7,
			"date": "2026-06-14",
			"day": "Sunday",
			"time": "11:15",
			"homeTeamId": "3vmZv3YLmq",
			"awayTeamId": "1pN6pqv7d0",
			"homeTeamName": "Aintree SC U14 Juniors - D Mixed AINTREE BOYS",
			"awayTeamName": "Sunbury United FC U14 Juniors - D Mixed Sunbury United FC U14",
			"address": "Aintree North Recreation Reserve Field 1",
			"coordinates": "-37.714012,144.665373",
			"status": "pending"
		},
		{
			"round": 7,
			"date": "2026-06-14",
			"day": "Sunday",
			"time": "11:15",
			"homeTeamId": "kemAbxpxNB",
			"awayTeamId": "nPmrBk05mo",
			"homeTeamName": "Macedon Rangers SC U14 Juniors - D Mixed U14 Mixed Juniors MRSC",
			"awayTeamName": "Hoppers Crossing SC U14 Juniors - D Mixed u14 Frank",
			"address": "Romsey Recreation Reserve Pitch 2",
			"coordinates": "-37.353194,144.749117",
			"status": "pending"
		},
		{
			"round": 7,
			"date": "2026-06-14",
			"day": "Sunday",
			"time": "11:15",
			"homeTeamId": "R1K3BOqGNQ",
			"awayTeamId": "bgdMXLL2KE",
			"homeTeamName": "Satellite City United SC U14 Juniors - D Mixed Costa",
			"awayTeamName": "Barnstoneworth United FC U14 Juniors - D Mixed BUFC U14",
			"address": "Kurunjang Recreation Reserve Pitch 1 (S)",
			"coordinates": "-37.6742,144.584",
			"status": "pending"
		},
		{
			"round": 7,
			"date": "2026-06-14",
			"day": "Sunday",
			"time": "11:15",
			"homeTeamId": "AnmYzg4rNz",
			"awayTeamId": "gld4pGXGdW",
			"homeTeamName": "Maidstone United SC U14 Juniors - D Mixed Mick",
			"awayTeamName": "Gisborne SC U14 Juniors - D Mixed 14JS",
			"address": "Scovell Reserve Main Pitch",
			"coordinates": "-37.784639,144.878892",
			"status": "pending"
		},
		{
			"round": 7,
			"date": "2026-06-14",
			"day": "Sunday",
			"time": "11:15",
			"homeTeamId": "3vmZv9nLmq",
			"awayTeamId": "6lNbpDpwdx",
			"homeTeamName": "Moonee Valley Knights SC U14 Juniors - D Mixed Moonee Valley Knights U14 (David)",
			"awayTeamName": "Williamstown SC U14 Juniors - D Mixed Under 14D Boys",
			"address": "Avondale Heights Reserve Pitch 1",
			"coordinates": "-37.76242,144.858824",
			"status": "pending"
		},
		{
			"round": 7,
			"date": "2026-06-14",
			"day": "Sunday",
			"time": "11:30",
			"homeTeamId": "R1K3BvL3NQ",
			"awayTeamId": "Bjma0G03dR",
			"homeTeamName": "Melbourne City FC U14 Juniors - D Mixed",
			"awayTeamName": "Wyndham FC U14 Juniors - D Mixed Under 14 D",
			"address": "Edwards Reserve Main Pitch",
			"coordinates": "-37.827616,144.870036",
			"status": "pending"
		},
		{
			"round": 8,
			"date": "2026-06-20",
			"day": "Sunday",
			"time": "09:30",
			"homeTeamId": "6lNbpDpwdx",
			"awayTeamId": "R1K3BOqGNQ",
			"homeTeamName": "Williamstown SC U14 Juniors - D Mixed Under 14D Boys",
			"awayTeamName": "Satellite City United SC U14 Juniors - D Mixed Costa",
			"address": "JT Gray Reserve Pitch 1 - WSC",
			"coordinates": "-37.857002,144.865559",
			"status": "pending"
		},
		{
			"round": 8,
			"date": "2026-06-21",
			"day": "Sunday",
			"time": "10:00",
			"homeTeamId": "kemAbxpxNB",
			"awayTeamId": "3vmZv3YLmq",
			"homeTeamName": "Macedon Rangers SC U14 Juniors - D Mixed U14 Mixed Juniors MRSC",
			"awayTeamName": "Aintree SC U14 Juniors - D Mixed AINTREE BOYS",
			"address": "Romsey Recreation Reserve Pitch 2",
			"coordinates": "-37.353194,144.749117",
			"status": "pending"
		},
		{
			"round": 8,
			"date": "2026-06-21",
			"day": "Sunday",
			"time": "11:00",
			"homeTeamId": "Bjma0G03dR",
			"awayTeamId": "1pN6pqv7d0",
			"homeTeamName": "Wyndham FC U14 Juniors - D Mixed Under 14 D",
			"awayTeamName": "Sunbury United FC U14 Juniors - D Mixed Sunbury United FC U14",
			"address": "Wyndham Vale North Reserve Main Pitch A",
			"coordinates": "-37.898902,144.624443",
			"status": "pending"
		},
		{
			"round": 8,
			"date": "2026-06-21",
			"day": "Sunday",
			"time": "11:00",
			"homeTeamId": "gld4pGXGdW",
			"awayTeamId": "3vmZv9nLmq",
			"homeTeamName": "Gisborne SC U14 Juniors - D Mixed 14JS",
			"awayTeamName": "Moonee Valley Knights SC U14 Juniors - D Mixed Moonee Valley Knights U14 (David)",
			"address": "Dixon Field Reserve Pitch E (Junior)",
			"coordinates": "-37.483554,144.582761",
			"status": "pending"
		},
		{
			"round": 8,
			"date": "2026-06-21",
			"day": "Sunday",
			"time": "11:25",
			"homeTeamId": "nPmrBk05mo",
			"awayTeamId": "bam1nkkrNw",
			"homeTeamName": "Hoppers Crossing SC U14 Juniors - D Mixed u14 Frank",
			"awayTeamName": "Footscray Rangers FC U14 Juniors - C Mixed Martin",
			"address": "Grange Reserve - Hoppers Crossing Pitch 3 - Synthetic",
			"coordinates": "-37.861006,144.67653",
			"status": "pending"
		},
		{
			"round": 8,
			"date": "2026-06-21",
			"day": "Sunday",
			"time": "11:45",
			"homeTeamId": "bgdMXLL2KE",
			"awayTeamId": "R1K3BvL3NQ",
			"homeTeamName": "Barnstoneworth United FC U14 Juniors - D Mixed BUFC U14",
			"awayTeamName": "Melbourne City FC U14 Juniors - D Mixed",
			"address": "JT Gray Reserve Pitch 6- BUFC",
			"coordinates": "-37.857002,144.865559",
			"status": "pending"
		},
		{
			"round": 8,
			"date": "2026-06-21",
			"day": "Sunday",
			"time": "12:15",
			"homeTeamId": "k2KpRJ56mY",
			"awayTeamId": "AnmYzg4rNz",
			"homeTeamName": "Truganina Lions FC U14 Juniors - D Mixed Boys U14 - D",
			"awayTeamName": "Maidstone United SC U14 Juniors - D Mixed Mick",
			"address": "Alcock Road Reserve Pitch 2",
			"coordinates": "-37.829359,144.720192",
			"status": "pending"
		},
		{
			"round": 9,
			"date": "2026-06-28",
			"day": "Sunday",
			"time": "11:00",
			"homeTeamId": "bam1nkkrNw",
			"awayTeamId": "kemAbxpxNB",
			"homeTeamName": "Footscray Rangers FC U14 Juniors - C Mixed Martin",
			"awayTeamName": "Macedon Rangers SC U14 Juniors - D Mixed U14 Mixed Juniors MRSC",
			"address": "Hansen Reserve Pitch 2 - Junior Pitch",
			"coordinates": "-37.8042,144.872777",
			"status": "pending"
		},
		{
			"round": 9,
			"date": "2026-06-28",
			"day": "Sunday",
			"time": "11:00",
			"homeTeamId": "1pN6pqv7d0",
			"awayTeamId": "bgdMXLL2KE",
			"homeTeamName": "Sunbury United FC U14 Juniors - D Mixed Sunbury United FC U14",
			"awayTeamName": "Barnstoneworth United FC U14 Juniors - D Mixed BUFC U14",
			"address": "Langama Park Pitch 2 - Full Field",
			"coordinates": "-37.586728,144.709286",
			"status": "pending"
		},
		{
			"round": 9,
			"date": "2026-06-28",
			"day": "Sunday",
			"time": "11:15",
			"homeTeamId": "3vmZv3YLmq",
			"awayTeamId": "Bjma0G03dR",
			"homeTeamName": "Aintree SC U14 Juniors - D Mixed AINTREE BOYS",
			"awayTeamName": "Wyndham FC U14 Juniors - D Mixed Under 14 D",
			"address": "Aintree North Recreation Reserve Field 1",
			"coordinates": "-37.714012,144.665373",
			"status": "pending"
		},
		{
			"round": 9,
			"date": "2026-06-28",
			"day": "Sunday",
			"time": "11:15",
			"homeTeamId": "R1K3BOqGNQ",
			"awayTeamId": "gld4pGXGdW",
			"homeTeamName": "Satellite City United SC U14 Juniors - D Mixed Costa",
			"awayTeamName": "Gisborne SC U14 Juniors - D Mixed 14JS",
			"address": "Kurunjang Recreation Reserve Pitch 1 (S)",
			"coordinates": "-37.6742,144.584",
			"status": "pending"
		},
		{
			"round": 9,
			"date": "2026-06-28",
			"day": "Sunday",
			"time": "12:00",
			"homeTeamId": "R1K3BvL3NQ",
			"awayTeamId": "6lNbpDpwdx",
			"homeTeamName": "Melbourne City FC U14 Juniors - D Mixed",
			"awayTeamName": "Williamstown SC U14 Juniors - D Mixed Under 14D Boys",
			"address": "Edwards Reserve Main Pitch",
			"coordinates": "-37.827616,144.870036",
			"status": "pending"
		},
		{
			"round": 9,
			"date": "2026-06-28",
			"day": "Sunday",
			"time": "12:40",
			"homeTeamId": "AnmYzg4rNz",
			"awayTeamId": "nPmrBk05mo",
			"homeTeamName": "Maidstone United SC U14 Juniors - D Mixed Mick",
			"awayTeamName": "Hoppers Crossing SC U14 Juniors - D Mixed u14 Frank",
			"address": "Scovell Reserve Main Pitch",
			"coordinates": "-37.784639,144.878892",
			"status": "pending"
		},
		{
			"round": 9,
			"date": "2026-06-28",
			"day": "Sunday",
			"time": "13:45",
			"homeTeamId": "3vmZv9nLmq",
			"awayTeamId": "k2KpRJ56mY",
			"homeTeamName": "Moonee Valley Knights SC U14 Juniors - D Mixed Moonee Valley Knights U14 (David)",
			"awayTeamName": "Truganina Lions FC U14 Juniors - D Mixed Boys U14 - D",
			"address": "Avondale Heights Reserve Pitch 1",
			"coordinates": "-37.76242,144.858824",
			"status": "pending"
		},
		{
			"round": 10,
			"date": "2026-07-11",
			"day": "Sunday",
			"time": "09:00",
			"homeTeamId": "bgdMXLL2KE",
			"awayTeamId": "Bjma0G03dR",
			"homeTeamName": "Barnstoneworth United FC U14 Juniors - D Mixed BUFC U14",
			"awayTeamName": "Wyndham FC U14 Juniors - D Mixed Under 14 D",
			"address": "JT Gray Reserve Pitch 6- BUFC",
			"coordinates": "-37.857002,144.865559",
			"status": "pending"
		},
		{
			"round": 10,
			"date": "2026-07-12",
			"day": "Sunday",
			"time": "10:00",
			"homeTeamId": "6lNbpDpwdx",
			"awayTeamId": "1pN6pqv7d0",
			"homeTeamName": "Williamstown SC U14 Juniors - D Mixed Under 14D Boys",
			"awayTeamName": "Sunbury United FC U14 Juniors - D Mixed Sunbury United FC U14",
			"address": "JT Gray Reserve Pitch 1 - WSC",
			"coordinates": "-37.857002,144.865559",
			"status": "pending"
		},
		{
			"round": 10,
			"date": "2026-07-12",
			"day": "Sunday",
			"time": "10:00",
			"homeTeamId": "nPmrBk05mo",
			"awayTeamId": "3vmZv9nLmq",
			"homeTeamName": "Hoppers Crossing SC U14 Juniors - D Mixed u14 Frank",
			"awayTeamName": "Moonee Valley Knights SC U14 Juniors - D Mixed Moonee Valley Knights U14 (David)",
			"address": "Grange Reserve - Hoppers Crossing Pitch 1",
			"coordinates": "-37.861006,144.67653",
			"status": "pending"
		},
		{
			"round": 10,
			"date": "2026-07-12",
			"day": "Sunday",
			"time": "11:00",
			"homeTeamId": "kemAbxpxNB",
			"awayTeamId": "AnmYzg4rNz",
			"homeTeamName": "Macedon Rangers SC U14 Juniors - D Mixed U14 Mixed Juniors MRSC",
			"awayTeamName": "Maidstone United SC U14 Juniors - D Mixed Mick",
			"address": "Romsey Recreation Reserve Pitch 2",
			"coordinates": "-37.353194,144.749117",
			"status": "pending"
		},
		{
			"round": 10,
			"date": "2026-07-12",
			"day": "Sunday",
			"time": "11:00",
			"homeTeamId": "gld4pGXGdW",
			"awayTeamId": "R1K3BvL3NQ",
			"homeTeamName": "Gisborne SC U14 Juniors - D Mixed 14JS",
			"awayTeamName": "Melbourne City FC U14 Juniors - D Mixed",
			"address": "Dixon Field Reserve Pitch E (Junior)",
			"coordinates": "-37.483554,144.582761",
			"status": "pending"
		},
		{
			"round": 10,
			"date": "2026-07-12",
			"day": "Sunday",
			"time": "11:30",
			"homeTeamId": "bam1nkkrNw",
			"awayTeamId": "3vmZv3YLmq",
			"homeTeamName": "Footscray Rangers FC U14 Juniors - C Mixed Martin",
			"awayTeamName": "Aintree SC U14 Juniors - D Mixed AINTREE BOYS",
			"address": "Hansen Reserve Pitch 2 - Junior Pitch",
			"coordinates": "-37.8042,144.872777",
			"status": "pending"
		},
		{
			"round": 10,
			"date": "2026-07-12",
			"day": "Sunday",
			"time": "13:30",
			"homeTeamId": "k2KpRJ56mY",
			"awayTeamId": "R1K3BOqGNQ",
			"homeTeamName": "Truganina Lions FC U14 Juniors - D Mixed Boys U14 - D",
			"awayTeamName": "Satellite City United SC U14 Juniors - D Mixed Costa",
			"address": "Alcock Road Reserve Pitch 2",
			"coordinates": "-37.829359,144.720192",
			"status": "pending"
		},
		{
			"round": 11,
			"date": "2026-07-19",
			"day": "Sunday",
			"time": "10:00",
			"homeTeamId": "3vmZv3YLmq",
			"awayTeamId": "bgdMXLL2KE",
			"homeTeamName": "Aintree SC U14 Juniors - D Mixed AINTREE BOYS",
			"awayTeamName": "Barnstoneworth United FC U14 Juniors - D Mixed BUFC U14",
			"address": "Aintree North Recreation Reserve Field 2",
			"coordinates": "-37.714012,144.665373",
			"status": "pending"
		},
		{
			"round": 11,
			"date": "2026-07-19",
			"day": "Sunday",
			"time": "11:00",
			"homeTeamId": "3vmZv9nLmq",
			"awayTeamId": "kemAbxpxNB",
			"homeTeamName": "Moonee Valley Knights SC U14 Juniors - D Mixed Moonee Valley Knights U14 (David)",
			"awayTeamName": "Macedon Rangers SC U14 Juniors - D Mixed U14 Mixed Juniors MRSC",
			"address": "Avondale Heights Reserve Pitch 1",
			"coordinates": "-37.76242,144.858824",
			"status": "pending"
		},
		{
			"round": 11,
			"date": "2026-07-19",
			"day": "Sunday",
			"time": "11:00",
			"homeTeamId": "1pN6pqv7d0",
			"awayTeamId": "gld4pGXGdW",
			"homeTeamName": "Sunbury United FC U14 Juniors - D Mixed Sunbury United FC U14",
			"awayTeamName": "Gisborne SC U14 Juniors - D Mixed 14JS",
			"address": "Langama Park Pitch 2 - Full Field",
			"coordinates": "-37.586728,144.709286",
			"status": "pending"
		},
		{
			"round": 11,
			"date": "2026-07-19",
			"day": "Sunday",
			"time": "11:15",
			"homeTeamId": "R1K3BOqGNQ",
			"awayTeamId": "nPmrBk05mo",
			"homeTeamName": "Satellite City United SC U14 Juniors - D Mixed Costa",
			"awayTeamName": "Hoppers Crossing SC U14 Juniors - D Mixed u14 Frank",
			"address": "Kurunjang Recreation Reserve Pitch 1 (S)",
			"coordinates": "-37.6742,144.584",
			"status": "pending"
		},
		{
			"round": 11,
			"date": "2026-07-19",
			"day": "Sunday",
			"time": "12:30",
			"homeTeamId": "AnmYzg4rNz",
			"awayTeamId": "bam1nkkrNw",
			"homeTeamName": "Maidstone United SC U14 Juniors - D Mixed Mick",
			"awayTeamName": "Footscray Rangers FC U14 Juniors - C Mixed Martin",
			"address": "Scovell Reserve Main Pitch",
			"coordinates": "-37.784639,144.878892",
			"status": "pending"
		},
		{
			"round": 11,
			"date": "2026-07-19",
			"day": "Sunday",
			"time": "12:35",
			"homeTeamId": "R1K3BvL3NQ",
			"awayTeamId": "k2KpRJ56mY",
			"homeTeamName": "Melbourne City FC U14 Juniors - D Mixed",
			"awayTeamName": "Truganina Lions FC U14 Juniors - D Mixed Boys U14 - D",
			"address": "Edwards Reserve Main Pitch",
			"coordinates": "-37.827616,144.870036",
			"status": "pending"
		},
		{
			"round": 11,
			"date": "2026-07-19",
			"day": "Sunday",
			"time": "12:45",
			"homeTeamId": "Bjma0G03dR",
			"awayTeamId": "6lNbpDpwdx",
			"homeTeamName": "Wyndham FC U14 Juniors - D Mixed Under 14 D",
			"awayTeamName": "Williamstown SC U14 Juniors - D Mixed Under 14D Boys",
			"address": "Wyndham Vale North Reserve Main Pitch A",
			"coordinates": "-37.898902,144.624443",
			"status": "pending"
		},
		{
			"round": 12,
			"date": "2026-07-25",
			"day": "Sunday",
			"time": "09:30",
			"homeTeamId": "6lNbpDpwdx",
			"awayTeamId": "bgdMXLL2KE",
			"homeTeamName": "Williamstown SC U14 Juniors - D Mixed Under 14D Boys",
			"awayTeamName": "Barnstoneworth United FC U14 Juniors - D Mixed BUFC U14",
			"address": "JT Gray Reserve Pitch 1 - WSC",
			"coordinates": "-37.857002,144.865559",
			"status": "pending"
		},
		{
			"round": 12,
			"date": "2026-07-25",
			"day": "Sunday",
			"time": "09:45",
			"homeTeamId": "nPmrBk05mo",
			"awayTeamId": "R1K3BvL3NQ",
			"homeTeamName": "Hoppers Crossing SC U14 Juniors - D Mixed u14 Frank",
			"awayTeamName": "Melbourne City FC U14 Juniors - D Mixed",
			"address": "Grange Reserve - Hoppers Crossing Pitch 1",
			"coordinates": "-37.861006,144.67653",
			"status": "pending"
		},
		{
			"round": 12,
			"date": "2026-07-26",
			"day": "Sunday",
			"time": "10:35",
			"homeTeamId": "AnmYzg4rNz",
			"awayTeamId": "3vmZv3YLmq",
			"homeTeamName": "Maidstone United SC U14 Juniors - D Mixed Mick",
			"awayTeamName": "Aintree SC U14 Juniors - D Mixed AINTREE BOYS",
			"address": "Scovell Reserve Main Pitch",
			"coordinates": "-37.784639,144.878892",
			"status": "pending"
		},
		{
			"round": 12,
			"date": "2026-07-26",
			"day": "Sunday",
			"time": "11:15",
			"homeTeamId": "kemAbxpxNB",
			"awayTeamId": "R1K3BOqGNQ",
			"homeTeamName": "Macedon Rangers SC U14 Juniors - D Mixed U14 Mixed Juniors MRSC",
			"awayTeamName": "Satellite City United SC U14 Juniors - D Mixed Costa",
			"address": "Romsey Recreation Reserve Pitch 2",
			"coordinates": "-37.353194,144.749117",
			"status": "pending"
		},
		{
			"round": 12,
			"date": "2026-07-26",
			"day": "Sunday",
			"time": "11:30",
			"homeTeamId": "bam1nkkrNw",
			"awayTeamId": "3vmZv9nLmq",
			"homeTeamName": "Footscray Rangers FC U14 Juniors - C Mixed Martin",
			"awayTeamName": "Moonee Valley Knights SC U14 Juniors - D Mixed Moonee Valley Knights U14 (David)",
			"address": "Hansen Reserve Pitch 2 - Junior Pitch",
			"coordinates": "-37.8042,144.872777",
			"status": "pending"
		},
		{
			"round": 12,
			"date": "2026-07-26",
			"day": "Sunday",
			"time": "12:40",
			"homeTeamId": "gld4pGXGdW",
			"awayTeamId": "Bjma0G03dR",
			"homeTeamName": "Gisborne SC U14 Juniors - D Mixed 14JS",
			"awayTeamName": "Wyndham FC U14 Juniors - D Mixed Under 14 D",
			"address": "Dixon Field Reserve Pitch E (Junior)",
			"coordinates": "-37.483554,144.582761",
			"status": "pending"
		},
		{
			"round": 12,
			"date": "2026-07-26",
			"day": "Sunday",
			"time": "13:45",
			"homeTeamId": "k2KpRJ56mY",
			"awayTeamId": "1pN6pqv7d0",
			"homeTeamName": "Truganina Lions FC U14 Juniors - D Mixed Boys U14 - D",
			"awayTeamName": "Sunbury United FC U14 Juniors - D Mixed Sunbury United FC U14",
			"address": "Alcock Road Reserve Pitch 3",
			"coordinates": "-37.829359,144.720192",
			"status": "pending"
		},
		{
			"round": 13,
			"date": "2026-08-02",
			"day": "Sunday",
			"time": "10:15",
			"homeTeamId": "bgdMXLL2KE",
			"awayTeamId": "gld4pGXGdW",
			"homeTeamName": "Barnstoneworth United FC U14 Juniors - D Mixed BUFC U14",
			"awayTeamName": "Gisborne SC U14 Juniors - D Mixed 14JS",
			"address": "JT Gray Reserve Pitch 6- BUFC",
			"coordinates": "-37.857002,144.865559",
			"status": "pending"
		},
		{
			"round": 13,
			"date": "2026-08-02",
			"day": "Sunday",
			"time": "11:00",
			"homeTeamId": "1pN6pqv7d0",
			"awayTeamId": "nPmrBk05mo",
			"homeTeamName": "Sunbury United FC U14 Juniors - D Mixed Sunbury United FC U14",
			"awayTeamName": "Hoppers Crossing SC U14 Juniors - D Mixed u14 Frank",
			"address": "Langama Park Pitch 2 - Full Field",
			"coordinates": "-37.586728,144.709286",
			"status": "pending"
		},
		{
			"round": 13,
			"date": "2026-08-02",
			"day": "Sunday",
			"time": "11:15",
			"homeTeamId": "3vmZv9nLmq",
			"awayTeamId": "AnmYzg4rNz",
			"homeTeamName": "Moonee Valley Knights SC U14 Juniors - D Mixed Moonee Valley Knights U14 (David)",
			"awayTeamName": "Maidstone United SC U14 Juniors - D Mixed Mick",
			"address": "Avondale Heights Reserve Pitch 1",
			"coordinates": "-37.76242,144.858824",
			"status": "pending"
		},
		{
			"round": 13,
			"date": "2026-08-02",
			"day": "Sunday",
			"time": "11:15",
			"homeTeamId": "R1K3BOqGNQ",
			"awayTeamId": "bam1nkkrNw",
			"homeTeamName": "Satellite City United SC U14 Juniors - D Mixed Costa",
			"awayTeamName": "Footscray Rangers FC U14 Juniors - C Mixed Martin",
			"address": "Kurunjang Recreation Reserve Pitch 1 (S)",
			"coordinates": "-37.6742,144.584",
			"status": "pending"
		},
		{
			"round": 13,
			"date": "2026-08-02",
			"day": "Sunday",
			"time": "11:30",
			"homeTeamId": "3vmZv3YLmq",
			"awayTeamId": "6lNbpDpwdx",
			"homeTeamName": "Aintree SC U14 Juniors - D Mixed AINTREE BOYS",
			"awayTeamName": "Williamstown SC U14 Juniors - D Mixed Under 14D Boys",
			"address": "Aintree North Recreation Reserve Field 2",
			"coordinates": "-37.714012,144.665373",
			"status": "pending"
		},
		{
			"round": 13,
			"date": "2026-08-02",
			"day": "Sunday",
			"time": "12:00",
			"homeTeamId": "Bjma0G03dR",
			"awayTeamId": "k2KpRJ56mY",
			"homeTeamName": "Wyndham FC U14 Juniors - D Mixed Under 14 D",
			"awayTeamName": "Truganina Lions FC U14 Juniors - D Mixed Boys U14 - D",
			"address": "Wyndham Vale North Reserve Main Pitch A",
			"coordinates": "-37.898902,144.624443",
			"status": "pending"
		},
		{
			"round": 13,
			"date": "2026-08-02",
			"day": "Sunday",
			"time": "12:00",
			"homeTeamId": "R1K3BvL3NQ",
			"awayTeamId": "kemAbxpxNB",
			"homeTeamName": "Melbourne City FC U14 Juniors - D Mixed",
			"awayTeamName": "Macedon Rangers SC U14 Juniors - D Mixed U14 Mixed Juniors MRSC",
			"address": "Edwards Reserve Main Pitch",
			"coordinates": "-37.827616,144.870036",
			"status": "pending"
		},
		{
			"round": 14,
			"date": "2026-08-08",
			"day": "Sunday",
			"time": "09:00",
			"homeTeamId": "6lNbpDpwdx",
			"awayTeamId": "gld4pGXGdW",
			"homeTeamName": "Williamstown SC U14 Juniors - D Mixed Under 14D Boys",
			"awayTeamName": "Gisborne SC U14 Juniors - D Mixed 14JS",
			"address": "JT Gray Reserve Pitch 1 - WSC",
			"coordinates": "-37.857002,144.865559",
			"status": "pending"
		},
		{
			"round": 14,
			"date": "2026-08-09",
			"day": "Sunday",
			"time": "10:15",
			"homeTeamId": "bgdMXLL2KE",
			"awayTeamId": "k2KpRJ56mY",
			"homeTeamName": "Barnstoneworth United FC U14 Juniors - D Mixed BUFC U14",
			"awayTeamName": "Truganina Lions FC U14 Juniors - D Mixed Boys U14 - D",
			"address": "JT Gray Reserve Pitch 6- BUFC",
			"coordinates": "-37.857002,144.865559",
			"status": "pending"
		},
		{
			"round": 14,
			"date": "2026-08-09",
			"day": "Sunday",
			"time": "11:00",
			"homeTeamId": "1pN6pqv7d0",
			"awayTeamId": "kemAbxpxNB",
			"homeTeamName": "Sunbury United FC U14 Juniors - D Mixed Sunbury United FC U14",
			"awayTeamName": "Macedon Rangers SC U14 Juniors - D Mixed U14 Mixed Juniors MRSC",
			"address": "Langama Park Pitch 2 - Full Field",
			"coordinates": "-37.586728,144.709286",
			"status": "pending"
		},
		{
			"round": 14,
			"date": "2026-08-09",
			"day": "Sunday",
			"time": "11:15",
			"homeTeamId": "R1K3BOqGNQ",
			"awayTeamId": "AnmYzg4rNz",
			"homeTeamName": "Satellite City United SC U14 Juniors - D Mixed Costa",
			"awayTeamName": "Maidstone United SC U14 Juniors - D Mixed Mick",
			"address": "Kurunjang Recreation Reserve Pitch 1 (S)",
			"coordinates": "-37.6742,144.584",
			"status": "pending"
		},
		{
			"round": 14,
			"date": "2026-08-09",
			"day": "Sunday",
			"time": "11:15",
			"homeTeamId": "Bjma0G03dR",
			"awayTeamId": "nPmrBk05mo",
			"homeTeamName": "Wyndham FC U14 Juniors - D Mixed Under 14 D",
			"awayTeamName": "Hoppers Crossing SC U14 Juniors - D Mixed u14 Frank",
			"address": "Wyndham Vale North Reserve Main Pitch A",
			"coordinates": "-37.898902,144.624443",
			"status": "pending"
		},
		{
			"round": 14,
			"date": "2026-08-09",
			"day": "Sunday",
			"time": "12:00",
			"homeTeamId": "R1K3BvL3NQ",
			"awayTeamId": "bam1nkkrNw",
			"homeTeamName": "Melbourne City FC U14 Juniors - D Mixed",
			"awayTeamName": "Footscray Rangers FC U14 Juniors - C Mixed Martin",
			"address": "Edwards Reserve Main Pitch",
			"coordinates": "-37.827616,144.870036",
			"status": "pending"
		},
		{
			"round": 14,
			"date": "2026-08-09",
			"day": "Sunday",
			"time": "12:30",
			"homeTeamId": "3vmZv9nLmq",
			"awayTeamId": "3vmZv3YLmq",
			"homeTeamName": "Moonee Valley Knights SC U14 Juniors - D Mixed Moonee Valley Knights U14 (David)",
			"awayTeamName": "Aintree SC U14 Juniors - D Mixed AINTREE BOYS",
			"address": "Avondale Heights Reserve Pitch 1",
			"coordinates": "-37.76242,144.858824",
			"status": "pending"
		},
		{
			"round": 15,
			"date": "2026-08-16",
			"day": "Sunday",
			"time": "10:20",
			"homeTeamId": "3vmZv3YLmq",
			"awayTeamId": "gld4pGXGdW",
			"homeTeamName": "Aintree SC U14 Juniors - D Mixed AINTREE BOYS",
			"awayTeamName": "Gisborne SC U14 Juniors - D Mixed 14JS",
			"address": "Aintree North Recreation Reserve Field 1",
			"coordinates": "-37.714012,144.665373",
			"status": "pending"
		},
		{
			"round": 15,
			"date": "2026-08-16",
			"day": "Sunday",
			"time": "10:30",
			"homeTeamId": "nPmrBk05mo",
			"awayTeamId": "bgdMXLL2KE",
			"homeTeamName": "Hoppers Crossing SC U14 Juniors - D Mixed u14 Frank",
			"awayTeamName": "Barnstoneworth United FC U14 Juniors - D Mixed BUFC U14",
			"address": "Grange Reserve - Hoppers Crossing Pitch 2",
			"coordinates": "-37.861006,144.67653",
			"status": "pending"
		},
		{
			"round": 15,
			"date": "2026-08-16",
			"day": "Sunday",
			"time": "10:35",
			"homeTeamId": "AnmYzg4rNz",
			"awayTeamId": "R1K3BvL3NQ",
			"homeTeamName": "Maidstone United SC U14 Juniors - D Mixed Mick",
			"awayTeamName": "Melbourne City FC U14 Juniors - D Mixed",
			"address": "Scovell Reserve Main Pitch",
			"coordinates": "-37.784639,144.878892",
			"status": "pending"
		},
		{
			"round": 15,
			"date": "2026-08-16",
			"day": "Sunday",
			"time": "11:00",
			"homeTeamId": "bam1nkkrNw",
			"awayTeamId": "1pN6pqv7d0",
			"homeTeamName": "Footscray Rangers FC U14 Juniors - C Mixed Martin",
			"awayTeamName": "Sunbury United FC U14 Juniors - D Mixed Sunbury United FC U14",
			"address": "Hansen Reserve Pitch 2 - Junior Pitch",
			"coordinates": "-37.8042,144.872777",
			"status": "pending"
		},
		{
			"round": 15,
			"date": "2026-08-16",
			"day": "Sunday",
			"time": "11:00",
			"homeTeamId": "kemAbxpxNB",
			"awayTeamId": "Bjma0G03dR",
			"homeTeamName": "Macedon Rangers SC U14 Juniors - D Mixed U14 Mixed Juniors MRSC",
			"awayTeamName": "Wyndham FC U14 Juniors - D Mixed Under 14 D",
			"address": "Romsey Recreation Reserve Pitch 2",
			"coordinates": "-37.353194,144.749117",
			"status": "pending"
		},
		{
			"round": 15,
			"date": "2026-08-16",
			"day": "Sunday",
			"time": "11:15",
			"homeTeamId": "3vmZv9nLmq",
			"awayTeamId": "R1K3BOqGNQ",
			"homeTeamName": "Moonee Valley Knights SC U14 Juniors - D Mixed Moonee Valley Knights U14 (David)",
			"awayTeamName": "Satellite City United SC U14 Juniors - D Mixed Costa",
			"address": "Avondale Heights Reserve Pitch 1",
			"coordinates": "-37.76242,144.858824",
			"status": "pending"
		},
		{
			"round": 15,
			"date": "2026-08-16",
			"day": "Sunday",
			"time": "13:30",
			"homeTeamId": "k2KpRJ56mY",
			"awayTeamId": "6lNbpDpwdx",
			"homeTeamName": "Truganina Lions FC U14 Juniors - D Mixed Boys U14 - D",
			"awayTeamName": "Williamstown SC U14 Juniors - D Mixed Under 14D Boys",
			"address": "Alcock Road Reserve Pitch 2",
			"coordinates": "-37.829359,144.720192",
			"status": "pending"
		},
		{
			"round": 16,
			"date": "2026-08-22",
			"day": "Sunday",
			"time": "08:45",
			"homeTeamId": "6lNbpDpwdx",
			"awayTeamId": "nPmrBk05mo",
			"homeTeamName": "Williamstown SC U14 Juniors - D Mixed Under 14D Boys",
			"awayTeamName": "Hoppers Crossing SC U14 Juniors - D Mixed u14 Frank",
			"address": "JT Gray Reserve Pitch 1 - WSC",
			"coordinates": "-37.857002,144.865559",
			"status": "pending"
		},
		{
			"round": 16,
			"date": "2026-08-22",
			"day": "Sunday",
			"time": "09:00",
			"homeTeamId": "1pN6pqv7d0",
			"awayTeamId": "AnmYzg4rNz",
			"homeTeamName": "Sunbury United FC U14 Juniors - D Mixed Sunbury United FC U14",
			"awayTeamName": "Maidstone United SC U14 Juniors - D Mixed Mick",
			"address": "Langama Park Pitch 2 - Full Field",
			"coordinates": "-37.586728,144.709286",
			"status": "pending"
		},
		{
			"round": 16,
			"date": "2026-08-22",
			"day": "Sunday",
			"time": "09:35",
			"homeTeamId": "bgdMXLL2KE",
			"awayTeamId": "kemAbxpxNB",
			"homeTeamName": "Barnstoneworth United FC U14 Juniors - D Mixed BUFC U14",
			"awayTeamName": "Macedon Rangers SC U14 Juniors - D Mixed U14 Mixed Juniors MRSC",
			"address": "JT Gray Reserve Pitch 6- BUFC",
			"coordinates": "-37.857002,144.865559",
			"status": "pending"
		},
		{
			"round": 16,
			"date": "2026-08-23",
			"day": "Sunday",
			"time": "10:30",
			"homeTeamId": "Bjma0G03dR",
			"awayTeamId": "bam1nkkrNw",
			"homeTeamName": "Wyndham FC U14 Juniors - D Mixed Under 14 D",
			"awayTeamName": "Footscray Rangers FC U14 Juniors - C Mixed Martin",
			"address": "Wyndham Vale North Reserve Main Pitch A",
			"coordinates": "-37.898902,144.624443",
			"status": "pending"
		},
		{
			"round": 16,
			"date": "2026-08-23",
			"day": "Sunday",
			"time": "11:00",
			"homeTeamId": "gld4pGXGdW",
			"awayTeamId": "k2KpRJ56mY",
			"homeTeamName": "Gisborne SC U14 Juniors - D Mixed 14JS",
			"awayTeamName": "Truganina Lions FC U14 Juniors - D Mixed Boys U14 - D",
			"address": "Dixon Field Reserve Pitch E (Junior)",
			"coordinates": "-37.483554,144.582761",
			"status": "pending"
		},
		{
			"round": 16,
			"date": "2026-08-23",
			"day": "Sunday",
			"time": "11:15",
			"homeTeamId": "R1K3BOqGNQ",
			"awayTeamId": "3vmZv3YLmq",
			"homeTeamName": "Satellite City United SC U14 Juniors - D Mixed Costa",
			"awayTeamName": "Aintree SC U14 Juniors - D Mixed AINTREE BOYS",
			"address": "Kurunjang Recreation Reserve Pitch 1 (S)",
			"coordinates": "-37.6742,144.584",
			"status": "pending"
		},
		{
			"round": 16,
			"date": "2026-08-23",
			"day": "Sunday",
			"time": "12:00",
			"homeTeamId": "R1K3BvL3NQ",
			"awayTeamId": "3vmZv9nLmq",
			"homeTeamName": "Melbourne City FC U14 Juniors - D Mixed",
			"awayTeamName": "Moonee Valley Knights SC U14 Juniors - D Mixed Moonee Valley Knights U14 (David)",
			"address": "Edwards Reserve Main Pitch",
			"coordinates": "-37.827616,144.870036",
			"status": "pending"
		},
		{
			"round": 17,
			"date": "2026-08-30",
			"day": "Sunday",
			"time": "10:30",
			"homeTeamId": "nPmrBk05mo",
			"awayTeamId": "gld4pGXGdW",
			"homeTeamName": "Hoppers Crossing SC U14 Juniors - D Mixed u14 Frank",
			"awayTeamName": "Gisborne SC U14 Juniors - D Mixed 14JS",
			"address": "Grange Reserve - Hoppers Crossing Pitch 2",
			"coordinates": "-37.861006,144.67653",
			"status": "pending"
		},
		{
			"round": 17,
			"date": "2026-08-30",
			"day": "Sunday",
			"time": "11:00",
			"homeTeamId": "bam1nkkrNw",
			"awayTeamId": "bgdMXLL2KE",
			"homeTeamName": "Footscray Rangers FC U14 Juniors - C Mixed Martin",
			"awayTeamName": "Barnstoneworth United FC U14 Juniors - D Mixed BUFC U14",
			"address": "Hansen Reserve Pitch 1 - Senior Pitch",
			"coordinates": "-37.8042,144.872777",
			"status": "pending"
		},
		{
			"round": 17,
			"date": "2026-08-30",
			"day": "Sunday",
			"time": "11:15",
			"homeTeamId": "3vmZv3YLmq",
			"awayTeamId": "k2KpRJ56mY",
			"homeTeamName": "Aintree SC U14 Juniors - D Mixed AINTREE BOYS",
			"awayTeamName": "Truganina Lions FC U14 Juniors - D Mixed Boys U14 - D",
			"address": "Aintree North Recreation Reserve Field 1",
			"coordinates": "-37.714012,144.665373",
			"status": "pending"
		},
		{
			"round": 17,
			"date": "2026-08-30",
			"day": "Sunday",
			"time": "11:15",
			"homeTeamId": "R1K3BOqGNQ",
			"awayTeamId": "R1K3BvL3NQ",
			"homeTeamName": "Satellite City United SC U14 Juniors - D Mixed Costa",
			"awayTeamName": "Melbourne City FC U14 Juniors - D Mixed",
			"address": "Kurunjang Recreation Reserve Pitch 1 (S)",
			"coordinates": "-37.6742,144.584",
			"status": "pending"
		},
		{
			"round": 17,
			"date": "2026-08-30",
			"day": "Sunday",
			"time": "11:15",
			"homeTeamId": "3vmZv9nLmq",
			"awayTeamId": "1pN6pqv7d0",
			"homeTeamName": "Moonee Valley Knights SC U14 Juniors - D Mixed Moonee Valley Knights U14 (David)",
			"awayTeamName": "Sunbury United FC U14 Juniors - D Mixed Sunbury United FC U14",
			"address": "Avondale Heights Reserve Pitch 1",
			"coordinates": "-37.76242,144.858824",
			"status": "pending"
		},
		{
			"round": 17,
			"date": "2026-08-30",
			"day": "Sunday",
			"time": "11:15",
			"homeTeamId": "kemAbxpxNB",
			"awayTeamId": "6lNbpDpwdx",
			"homeTeamName": "Macedon Rangers SC U14 Juniors - D Mixed U14 Mixed Juniors MRSC",
			"awayTeamName": "Williamstown SC U14 Juniors - D Mixed Under 14D Boys",
			"address": "Romsey Recreation Reserve Pitch 2",
			"coordinates": "-37.353194,144.749117",
			"status": "pending"
		},
		{
			"round": 17,
			"date": "2026-08-30",
			"day": "Sunday",
			"time": "12:00",
			"homeTeamId": "AnmYzg4rNz",
			"awayTeamId": "Bjma0G03dR",
			"homeTeamName": "Maidstone United SC U14 Juniors - D Mixed Mick",
			"awayTeamName": "Wyndham FC U14 Juniors - D Mixed Under 14 D",
			"address": "Scovell Reserve Main Pitch",
			"coordinates": "-37.784639,144.878892",
			"status": "pending"
		},
		{
			"round": 18,
			"date": "2026-09-05",
			"day": "Sunday",
			"time": "08:45",
			"homeTeamId": "6lNbpDpwdx",
			"awayTeamId": "bam1nkkrNw",
			"homeTeamName": "Williamstown SC U14 Juniors - D Mixed Under 14D Boys",
			"awayTeamName": "Footscray Rangers FC U14 Juniors - C Mixed Martin",
			"address": "JT Gray Reserve Pitch 1 - WSC",
			"coordinates": "-37.857002,144.865559",
			"status": "pending"
		},
		{
			"round": 18,
			"date": "2026-09-06",
			"day": "Sunday",
			"time": "10:15",
			"homeTeamId": "1pN6pqv7d0",
			"awayTeamId": "R1K3BOqGNQ",
			"homeTeamName": "Sunbury United FC U14 Juniors - D Mixed Sunbury United FC U14",
			"awayTeamName": "Satellite City United SC U14 Juniors - D Mixed Costa",
			"address": "Langama Park Pitch 2 - Full Field",
			"coordinates": "-37.586728,144.709286",
			"status": "pending"
		},
		{
			"round": 18,
			"date": "2026-09-06",
			"day": "Sunday",
			"time": "10:20",
			"homeTeamId": "bgdMXLL2KE",
			"awayTeamId": "AnmYzg4rNz",
			"homeTeamName": "Barnstoneworth United FC U14 Juniors - D Mixed BUFC U14",
			"awayTeamName": "Maidstone United SC U14 Juniors - D Mixed Mick",
			"address": "JT Gray Reserve Pitch 6- BUFC",
			"coordinates": "-37.857002,144.865559",
			"status": "pending"
		},
		{
			"round": 18,
			"date": "2026-09-06",
			"day": "Sunday",
			"time": "11:00",
			"homeTeamId": "gld4pGXGdW",
			"awayTeamId": "kemAbxpxNB",
			"homeTeamName": "Gisborne SC U14 Juniors - D Mixed 14JS",
			"awayTeamName": "Macedon Rangers SC U14 Juniors - D Mixed U14 Mixed Juniors MRSC",
			"address": "Dixon Field Reserve Pitch E (Junior)",
			"coordinates": "-37.483554,144.582761",
			"status": "pending"
		},
		{
			"round": 18,
			"date": "2026-09-06",
			"day": "Sunday",
			"time": "12:15",
			"homeTeamId": "k2KpRJ56mY",
			"awayTeamId": "nPmrBk05mo",
			"homeTeamName": "Truganina Lions FC U14 Juniors - D Mixed Boys U14 - D",
			"awayTeamName": "Hoppers Crossing SC U14 Juniors - D Mixed u14 Frank",
			"address": "Alcock Road Reserve Pitch 2",
			"coordinates": "-37.829359,144.720192",
			"status": "pending"
		},
		{
			"round": 18,
			"date": "2026-09-06",
			"day": "Sunday",
			"time": "12:30",
			"homeTeamId": "Bjma0G03dR",
			"awayTeamId": "3vmZv9nLmq",
			"homeTeamName": "Wyndham FC U14 Juniors - D Mixed Under 14 D",
			"awayTeamName": "Moonee Valley Knights SC U14 Juniors - D Mixed Moonee Valley Knights U14 (David)",
			"address": "Wyndham Vale North Reserve Main Pitch B",
			"coordinates": "-37.898902,144.624443",
			"status": "pending"
		},
		{
			"round": 18,
			"date": "2026-09-06",
			"day": "Sunday",
			"time": "13:00",
			"homeTeamId": "R1K3BvL3NQ",
			"awayTeamId": "3vmZv3YLmq",
			"homeTeamName": "Melbourne City FC U14 Juniors - D Mixed",
			"awayTeamName": "Aintree SC U14 Juniors - D Mixed AINTREE BOYS",
			"address": "Edwards Reserve Main Pitch",
			"coordinates": "-37.827616,144.870036",
			"status": "pending"
		}
	]
}
