{
	"season": 2026,
	"competition": "Mixed Sunday West 13D Blue",
	"entries": [
		{
			"teamId": "nmYZ7RapNz",
			"teamName": "Barnstoneworth United FC U13 Juniors - D Mixed BUFC U13 Gold",
			"clubName": "Barnstoneworth United FC",
			"logoUrl": "https://ocean.dribl.com/fa250c47c9904e3496de00a27664dacc",
			"position": 1,
			"played": 1,
			"wins": 1,
			"draws": 0,
			"losses": 0,
			"goalsFor": 9,
			"goalsAgainst": 0,
			"goalDifference": 9,
			"points": 3
		},
		{
			"teamId": "ZKRPZ6Wymk",
			"teamName": "Williamstown SC U13 Juniors - D Mixed Under 13D Boys",
			"clubName": "Williamstown SC",
			"logoUrl": "https://ocean.dribl.com/355d84adb48649a0b4d562d8fa98c2bc",
			"position": 2,
			"played": 1,
			"wins": 1,
			"draws": 0,
			"losses": 0,
			"goalsFor": 3,
			"goalsAgainst": 1,
			"goalDifference": 2,
			"points": 3
		},
		{
			"teamId": "1K3v3Lk7NQ",
			"teamName": "Laverton FC U13 Juniors - D Mixed Laverton FC U13",
			"clubName": "Laverton FC",
			"logoUrl": "https://ocean.dribl.com/39543e69e63546e88b5e228b21717c94",
			"position": 3,
			"played": 0,
			"wins": 0,
			"draws": 0,
			"losses": 0,
			"goalsFor": 0,
			"goalsAgainst": 0,
			"goalDifference": 0,
			"points": 0
		},
		{
			"teamId": "8Nq73QQyd9",
			"teamName": "Truganina Lions FC U13 Juniors - D Mixed Boys U13 - D",
			"clubName": "Truganina Lions FC",
			"logoUrl": "https://ocean.dribl.com/8b70371c5f4b46929d72b03609d3280d",
			"position": 4,
			"played": 0,
			"wins": 0,
			"draws": 0,
			"losses": 0,
			"goalsFor": 0,
			"goalsAgainst": 0,
			"goalDifference": 0,
			"points": 0
		},
		{
			"teamId": "OmeX7rOvd0",
			"teamName": "Truganina Lions FC U13 Juniors - D Mixed Boys U13 - E",
			"clubName": "Truganina Lions FC",
			"logoUrl": "https://ocean.dribl.com/8b70371c5f4b46929d72b03609d3280d",
			"position": 5,
			"played": 0,
			"wins": 0,
			"draws": 0,
			"losses": 0,
			"goalsFor": 0,
			"goalsAgainst": 0,
			"goalDifference": 0,
			"points": 0
		},
		{
			"teamId": "emAe5MMxmB",
			"teamName": "Hoppers Crossing SC U13 Juniors - D Mixed u13 Dennis",
			"clubName": "Hoppers Crossing SC",
			"logoUrl": "https://ocean.dribl.com/6c3e2b0fde7442d7bf2f746b93b794b0",
			"position": 6,
			"played": 0,
			"wins": 0,
			"draws": 0,
			"losses": 0,
			"goalsFor": 0,
			"goalsAgainst": 0,
			"goalDifference": 0,
			"points": 0
		},
		{
			"teamId": "pmvwjVLoNv",
			"teamName": "Hoppers Crossing SC U13 Juniors - D Mixed u13 Dion",
			"clubName": "Hoppers Crossing SC",
			"logoUrl": "https://ocean.dribl.com/6c3e2b0fde7442d7bf2f746b93b794b0",
			"position": 7,
			"played": 0,
			"wins": 0,
			"draws": 0,
			"losses": 0,
			"goalsFor": 0,
			"goalsAgainst": 0,
			"goalDifference": 0,
			"points": 0
		},
		{
			"teamId": "gdME0g4QdE",
			"teamName": "West Point SC U13 Juniors - D Mixed U13D Mixed - Dumindu",
			"clubName": "West Point SC",
			"logoUrl": "https://ocean.dribl.com/98a1c928261d4c18b77ee3f8a7106e49",
			"position": 8,
			"played": 0,
			"wins": 0,
			"draws": 0,
			"losses": 0,
			"goalsFor": 0,
			"goalsAgainst": 0,
			"goalDifference": 0,
			"points": 0
		},
		{
			"teamId": "RdkEVqyRNG",
			"teamName": "Point Cook SC U13 Juniors - D Mixed U13 Falcons",
			"clubName": "Point Cook SC",
			"logoUrl": "https://ocean.dribl.com/b7c9554cb0b146e0ae696fe205418974",
			"position": 9,
			"played": 0,
			"wins": 0,
			"draws": 0,
			"losses": 0,
			"goalsFor": 0,
			"goalsAgainst": 0,
			"goalDifference": 0,
			"points": 0
		},
		{
			"teamId": "8Nq73zvgd9",
			"teamName": "Newport Storm FC U13 Juniors - D Mixed Zidane",
			"clubName": "Newport Storm FC",
			"logoUrl": "https://ocean.dribl.com/016071f6159842959c3a997cdfc93490",
			"position": 10,
			"played": 1,
			"wins": 0,
			"draws": 0,
			"losses": 1,
			"goalsFor": 1,
			"goalsAgainst": 3,
			"goalDifference": -2,
			"points": 0
		},
		{
			"teamId": "8dnEwP4pKw",
			"teamName": "Wyndham FC U13 Juniors - D Mixed U13 E",
			"clubName": "Wyndham FC",
			"logoUrl": "https://ocean.dribl.com/f20d0e1df69046dfb92cfe65f203cf7f",
			"position": 11,
			"played": 1,
			"wins": 0,
			"draws": 0,
			"losses": 1,
			"goalsFor": 0,
			"goalsAgainst": 9,
			"goalDifference": -9,
			"points": 0
		}
	]
}
